{
    "cluster_list": [
        {
            "cluster_name": "name3",
            "representative_sentences": [
                "rep0",
                "rep1",
                "rep2"
            ],
            "requests": [
                "what is covid",
                "what does covid stand for?",
                "what is covid?",
                "i heard about covid what is it?",
                "what is covid?",
                "what is covid?",
                "covid what is it",
                "what is covid?",
                "what is covid",
                "what is covid?",
                "what is covid",
                "what is covid?",
                "what is covid?",
                "what is covid"
            ]
        },
        {
            "cluster_name": "name35",
            "representative_sentences": [
                "rep0",
                "rep1",
                "rep2"
            ],
            "requests": [
                "when am i entitled to take paid sick leave?",
                "am i eligible for paid sick leave",
                "paid sick leave",
                "paid sick leave",
                "paid sick leave",
                "does my workplace offer paid sick leave?",
                "paid sick leave",
                "can i get paid sick leave",
                "paid sick leave",
                "who is able to get paid sick leave",
                "tell me about paid sick leave",
                "paid sick leave",
                "can i get paid sick leave",
                "do i get paid sick leave",
                "am i eligible for sick leave",
                "paid sick leave",
                "who is eligible to get paid sick leave"
            ]
        },
        {
            "cluster_name": "name39",
            "representative_sentences": [
                "rep0",
                "rep1",
                "rep2"
            ],
            "requests": [
                "when do the children go back to school",
                "when can kid go back to school",
                "when can i send my kids back to school",
                "when can my kids back school",
                "when can kids return to school",
                "when can my kids go back to school",
                "when will my kids be back in school?",
                "when can my kids go back to college?",
                "when can my kid go back to college",
                "when can my kid go back to school",
                "when can my kid go back school",
                "when can my kid go back to high school"
            ]
        },
        {
            "cluster_name": "name9",
            "representative_sentences": [
                "rep0",
                "rep1",
                "rep2"
            ],
            "requests": [
                "is there a test kit for coronavirus",
                "i want a coronavirus test",
                "is there a test kit for the coronavirus?",
                "i want a coronavirus test",
                "where can i get tested for coronavirus",
                "is there a test kit for the coronavirus",
                "is there test kit for coronavirus",
                "is there a coronavirus test kit",
                "i want a test for coronavirus",
                "how can i get a coronavirus test?",
                "where can i get tested for the coronavirus in new york",
                "coronavirus test kit",
                "is there a coronavirus test kit",
                "is there a test for teh coronavirus",
                "where can i get tested for coronavirus?",
                "is there a test for the coronavirus",
                "how do i get a coronavirus test?",
                "is there a test for coronavirus",
                "where can i get a coronavirus test",
                "coronavirus test kit",
                "coronavirus test kit",
                "where can i order a coronavirus test"
            ]
        },
        {
            "cluster_name": "name43",
            "representative_sentences": [
                "rep0",
                "rep1",
                "rep2"
            ],
            "requests": [
                "what are covid 19 symptoms",
                "what are the first symptoms for covid?",
                "what are the symptoms of covid-19",
                "what are covid 19 symptoms",
                "what are the symptoms of covid?",
                "what are the covid-19 symptoms?",
                "what are the covid-19 symptoms?",
                "what are the covid-19 symptoms?",
                "what are the symptoms of covid?",
                "what are the most common symptoms of covid?",
                "what are the early symptoms of covid-19?"
            ]
        },
        {
            "cluster_name": "name12",
            "representative_sentences": [
                "rep0",
                "rep1",
                "rep2"
            ],
            "requests": [
                "how to apply for unemployment",
                "how to apply for unemployment",
                "how do i apply for unemployment",
                "apply for unemployment",
                "i need to apply for unemployment.  how do i do it",
                "apply for unemployment",
                "how to i apply for unemployment",
                "how do i apply for unemployment",
                "apply for unemployment",
                "where can i apply for unemployment",
                "where can i apply for unemployment",
                "how can i apply for unemployment?",
                "how do i apply for unemployment benefits?",
                "how to i apply for unemployment"
            ]
        },
        {
            "cluster_name": "name15",
            "representative_sentences": [
                "rep0",
                "rep1",
                "rep2"
            ],
            "requests": [
                "what is covid19",
                "what is covid-19",
                "what is covid19",
                "what is covid-19",
                "what is covid-19\\",
                "what is covid-19?",
                "what is covid-19",
                "what is covid-19",
                "what is covid19",
                "what is covid19",
                "what is covid19",
                "what is covid-19\\",
                "what is covid-19\\",
                "what is covid-19\\",
                "what is covid-19",
                "what is covid-19\\",
                "what is covid-19\\",
                "what is covid-19\\",
                "what is covid-19"
            ]
        },
        {
            "cluster_name": "name16",
            "representative_sentences": [
                "rep0",
                "rep1",
                "rep2"
            ],
            "requests": [
                "what are symptoms",
                "what are my symptoms",
                "what are the symptoms?",
                "what are symptoms?",
                "what are the symptoms",
                "what are my symptoms",
                "what are symptoms?",
                "what are symptoms",
                "what are my symptoms",
                "hi what are the symptoms?",
                "what are the symptoms?",
                "what are symptoms",
                "what are the symptoms",
                "tell me about the symptoms",
                "what are the types of symptoms",
                "what are symptoms",
                "what are symptoms",
                "what are the symptoms?",
                "what are the symptoms",
                "what are the symptoms?",
                "what are the symptoms",
                "what are symptoms?",
                "what are the symptoms?",
                "what are the symptoms",
                "tell me about the symptoms",
                "what are symptoms?",
                "what are symptoms?",
                "what are my symptoms"
            ]
        },
        {
            "cluster_name": "name19",
            "representative_sentences": [
                "rep0",
                "rep1",
                "rep2"
            ],
            "requests": [
                "how does covid spread?",
                "how does covid spread",
                "how does covid spread?",
                "how does covid spread",
                "how is covid-19 spread?",
                "how does covid spread",
                "how does covid spread",
                "how does covid-19 spread",
                "how does covid spread",
                "how does covid-19 spread",
                "how does covid-19 spread to others",
                "how does covid spread?",
                "how is covid-19 spread?",
                "how does covid-19 spread"
            ]
        },
        {
            "cluster_name": "name20",
            "representative_sentences": [
                "rep0",
                "rep1",
                "rep2"
            ],
            "requests": [
                "what is the coronavirus?",
                "what'is corona virus",
                "what is corona virus?",
                "what is corona virus",
                "what is the corona virus",
                "what is corona virus",
                "what is the coronavirus?",
                "what'is corona virus",
                "what is the coronavirus?",
                "what is the corona virus?",
                "what is the coronavirus?",
                "what is corona virus?",
                "what is corona virus",
                "what is the corona virus?",
                "what is the corona virus",
                "what is novel coronavirus?",
                "what is corona virus",
                "what is corona virus",
                "what'is corona virus"
            ]
        },
        {
            "cluster_name": "name21",
            "representative_sentences": [
                "rep0",
                "rep1",
                "rep2"
            ],
            "requests": [
                "is covid19 contagious?",
                "is covid-19 contagious?",
                "how contagious is covid-19?",
                "is covid19 contagious?",
                "is covid-19 contagious?",
                "is covid19 contagious?",
                "is covid-19 contagious?",
                "is covid-19 contagious?",
                "is covid19 contagious?",
                "how contagious is covid-19?",
                "how contagious is covid-19?",
                "is covid19 contagious?",
                "is covid19 contagious?"
            ]
        },
        {
            "cluster_name": "name53",
            "representative_sentences": [
                "rep0",
                "rep1",
                "rep2"
            ],
            "requests": [
                "where can i test",
                "where can i get a test?",
                "where can i be tested",
                "where i can get tested",
                "where can i get a test done",
                "how do i get a test?",
                "where can i test",
                "where can i get a test",
                "where do i get a test",
                "where can i get tested?",
                "how can i get a test",
                "where can i get a test?",
                "where can i test",
                "where i can get tested",
                "where can i get a test",
                "how do i get a test?",
                "where do i get a test",
                "where can i test",
                "i need to get tested, where can i go?",
                "where can i get a test done?"
            ]
        },
        {
            "cluster_name": "name23",
            "representative_sentences": [
                "rep0",
                "rep1",
                "rep2"
            ],
            "requests": [
                "what's the difference between the flu and coronavirus",
                "what's the difference between flu and coronavirus?",
                "flu vs coronavirus",
                "flu vs coronavirus",
                "how's the flu different from coronavirus?",
                "flu vs coronavirus",
                "how's the flu different from coronavirus?",
                "what is different between flu and coronavirus",
                "flu vs coronavirus",
                "how is the flue different from the coronavirus?",
                "what is the difference between flu and coronavirus",
                "what is the difference between the flu and coronavirus",
                "what's the difference between flu and coronavirus"
            ]
        },
        {
            "cluster_name": "name25",
            "representative_sentences": [
                "rep0",
                "rep1",
                "rep2"
            ],
            "requests": [
                "is my school closed?",
                "is my kids school closed",
                "is the school closed",
                "are schools closed ?",
                "are my schools closed?",
                "is my kids school closed",
                "are schools closed in my area",
                "are schools closed ?",
                "are my children's schools closed?",
                "are schools closed ?",
                "what schools are closed",
                "is my kids school closed?",
                "are schools in my area closed",
                "is my kids school closed",
                "are my schools closed",
                "is the school closed",
                "are schools closed?",
                "is my kids school closed?",
                "what schools are closed",
                "which schools are closed?",
                "are my schools closed?",
                "which schools are closed?",
                "are my schools closed?",
                "are my schools closed?",
                "are my schools closed?",
                "what schools are closed",
                "is the school closed",
                "are schools closed",
                "is my school closed",
                "are schools shut down?",
                "are schools shut down?",
                "what schools are closed",
                "are schools in my area closed",
                "are schools closed?",
                "is my school closed?",
                "what schools are closed",
                "is my kids school closed?",
                "which schools are closed?",
                "are schools closed ?"
            ]
        },
        {
            "cluster_name": "name27",
            "representative_sentences": [
                "rep0",
                "rep1",
                "rep2"
            ],
            "requests": [
                "are schools open?",
                "are schools open?",
                "are schools open",
                "are schools open",
                "are schools open",
                "are schools open",
                "are schools open",
                "are schools open",
                "are schools open?",
                "are schools open?",
                "are schools open?",
                "are schools open"
            ]
        }
    ],
    "unclustered": [
        "i'd like a respirator",
        "can dogs get the corona virus?",
        "i was tested yesterday when do i hear back?",
        "how has coronavirus spread around the world?",
        "i'd like a respirator",
        "i suspect i have the virus who can i call?",
        "i hate this",
        "is this worse than flu",
        "what if i don't have paid sick leave?",
        "where can i get tested for corona?",
        "are my pets at risk from corona virus?",
        "are there any cases near me",
        "how can one know if they have been infected?",
        "i'm having respiratory problems",
        "can i return to the united states?",
        "can we go to the store?",
        "how many people have contracted the virus in pennysylvania",
        "how many people are infected",
        "is the covid vaccine ready?",
        "this is hateful",
        "i can't go to work.  can i get unemployment?",
        "i have sore throat",
        "is covid a disease?",
        "how can i avoid getting sick?",
        "i hate this",
        "what does the who do?",
        "what can you do",
        "flu vs covid19",
        "do i have to wear a mask when i'm outside or taking a walk?",
        "what happens after the ordered three-week closure period ends?",
        "do i need to get tested?",
        "how to avoid catching covid-19.",
        "how long do i have to stay in quarantine?",
        "how many cases of the virus are there in the world?",
        "can i go to grocery stores",
        "should i get tested for covid-19?",
        "when can i buy a mask?",
        "should i take theraflu?",
        "yes it is",
        "can i travel?",
        "do i need to get tested?",
        "should we get tested if we only have symptoms",
        "is there a vaccine for this",
        "i traveled to italy recently. what do i do?",
        "are the national parks closed?",
        "which countries are high risk to travel to?",
        "what can i ask you",
        "what are the crisis measures currently in place?",
        "do i have covid?",
        "everything is horrible",
        "what can you do",
        "how dangerous is this?",
        "how can i lower my temperature if i have the coronavirus?",
        "how many people are infected in the united states",
        "connect me to someone",
        "what can i do if i lose my job?",
        "how do i ensure my family is safe?",
        "how long do i have to self isolate if i have tested positive?",
        "how to treat covid?",
        "none of those sound like they cover how to get tested. can you tell me how/where i can get tested?",
        "does alcohol kill the coronavirus?",
        "when can my high school senior go back to school",
        "can pets get covid",
        "what medicines work best",
        "is covid dangerous to pregnant women?",
        "how many ppl are infected in the us?",
        "my friend has it should i t get tested",
        "what is recommended by who and other international organizations regarding coronavirus?",
        "which countries are affected by covid 19?",
        "can i protect myself by drinking alcohol",
        "i think i have covid 19",
        "i have a question about unemployment",
        "what if i live by myself and i'm in quarantine?",
        "when does covid vacation end?",
        "how long does the virus last",
        "how is covid transmitted?",
        "when will respirators and masks be finally sold?",
        "is there a vaccine for coronavirus?",
        "i'm in a covid-free area can i come back to the united states?",
        "number of infected",
        "do i need to disinfect my cell phone when i get home",
        "who you are?",
        "can i test myself?",
        "what is the mortality rate of covid-19",
        "is hs 123 open?",
        "this is crap",
        "who you are?",
        "how many people are infected in illinois?",
        "flu vs. covid-19",
        "can i get tested",
        "can i go to the store.",
        "i am a teacher / educator / employee of a school what restrictions apply to me?",
        "where can i get tested in houston?",
        "what are the covid symtoms",
        "flu vs. covid-19",
        "when will the nhl return?",
        "what sports are being cancelled?",
        "where can i get tested in new mexico",
        "can pets get the virus",
        "what is effective prevention against covid?",
        "is there a medication that can help me feel better?",
        "how many folks in texas are infected?",
        "i hate this",
        "when will the national emergency end?",
        "if i get sick will i continue to get paid?",
        "i don't like this",
        "is covid a disease?",
        "how can i protect my family from the spread of coronavirus?",
        "i hate this",
        "what should i do if i am a teacher?",
        "i'm afraid i have covid-19",
        "incubation period of coronavirus?",
        "is the coronavirus the same as sars?",
        "how can i prevent coronavirus",
        "when should i go to the hospital?",
        "what exactly is home quarantine?",
        "when will schools close?",
        "i need to get home from abroad, who can help me?",
        "which countries are quarantined",
        "how can i quarantine if i have family living with me?",
        "what cleaning regimen should i follow",
        "is there a vaccine for corona virus",
        "how can i get infected?",
        "when will my kids school reopen",
        "how are you",
        "my eyes are burning",
        "when will teaching go back to work?",
        "how do i get tested?",
        "what if i urgently need to take a flight?",
        "how long does the coronavirus last?",
        "should i go to the er if i have a cough",
        "i would like to get involved as a volunteer in the current situation but i do not know how to get involved.",
        "is it safe to go to costco?",
        "i want to help with babysitting.",
        "what does a pandemic mean?",
        "everything is horrible",
        "can we go to the store?",
        "testing spots for coronavirus?",
        "what should i do to stay safe?",
        "why are there no masks and respirators in pharmacies?",
        "is anyone near me sick",
        "i can not breath very well",
        "what can i do to avoid getting sick?",
        "will paid sick leave be available for uber drivers?",
        "is the government ready for covid",
        "when can i expect drugs for the virus?",
        "i think i'm infected",
        "are events being shut down?",
        "my husband has coronavirus symptoms",
        "will classes be moved to summer?",
        "what does a state of emergency mean?",
        "how to treat covid?",
        "i often travel by public transport. should i wear a respirator?",
        "will my employer give me paid leave if i have coronavirus?",
        "what\u2019s the best way to prevent coronavirus?",
        "i want to talk to someone.",
        "its been a week. who can i call to get my test results?",
        "i'm having respiratory problems",
        "how do you protect yourself?",
        "who you are?",
        "can i go shopping when i'm in quarantine?",
        "can i go to the grocery store?",
        "can dogs get covid19?",
        "how do i avoid coronavirus",
        "are grocery stores still open",
        "how does coronavirus spread?",
        "where cani get tested",
        "i want to be transferred",
        "what should i do",
        "how many people total have coronavirus?",
        "how do i clean my home properly?",
        "who are you",
        "what is the best prevention?",
        "i need help",
        "where did covid come from?",
        "when can i go outside",
        "how to treat covid?",
        "how many hospital beds are available in the united states?",
        "will a respirator help me?",
        "the who has declared a pandemic in the world. what does this mean?",
        "events and large gatherings",
        "events and large gatherings",
        "i think i'm infected",
        "how many people in the world have died?",
        "what is a pandemic?",
        "if i only have a sore throat is it coronavirus?",
        "under what conditions do i have to quarantine?",
        "are my kids going to die?",
        "can dogs get covid19?",
        "can i get infected if i receive a package",
        "what if i don't have paid sick leave",
        "how do i self quarantine ?",
        "how to prevent covid infection?",
        "they closed my school and i have nowhere to work.",
        "ok - i've got enough of those that i think i need to get tested.",
        "sars vs corona virus?",
        "how can i get screened",
        "flu vs covid19",
        "everything is horrible",
        "can i get tested?",
        "how do i get rid of germs at my home",
        "who is in danger",
        "i don't like this",
        "can i work from home?",
        "how many hospital beds do we have in the us?",
        "will there be a mandated quarantine",
        "what do i do if i don't have unemployment insurance?",
        "i want to be tested for covid-19",
        "what are the common symptoms",
        "can the dog get sick with corona virus?",
        "switch me to an operator",
        "how to i prevent myself from getting sick?",
        "what city parks are open?",
        "what is the treatment for this disease?",
        "will students still graduate this year?",
        "how are you",
        "i want to consult an expert.",
        "can someone come see me during quarantine?",
        "am i going to die?",
        "should i get tested",
        "is covid a disease?",
        "will my head hurt if i have covid 19?",
        "how is corona virus different than sars?",
        "when will masks be available?",
        "what does the ordered school closure mean for report cards?",
        "do i have to quarantine when i come back from out of the country?",
        "can pets contract the virus",
        "how many patients are infected with cornona virus in collin county",
        "this is crap",
        "what does breathlessness look like",
        "how long does it take for the virus to run through my system?",
        "how long can i get paid sick leave",
        "how is the us government addressing the spread of covid-19?",
        "is graduation delayed?",
        "i came back from a country do i have to quarantine?",
        "am i safe outside?",
        "how long does the disease last?",
        "are colleges open",
        "will a respirator help me?",
        "is it dangerous for postal workers",
        "will i get paid if i have covid-19?",
        "how do you protect yourself?",
        "i need help",
        "are the local parks open?",
        "what can i do if i lose my job",
        "how many people are infected",
        "are the local parks open?",
        "is there a vaccine for covid-19",
        "should i wear a mask so i don't get infected?",
        "how do you test",
        "i don't like this",
        "my throat hurts and i have a headache as well",
        "how do i prevent catching the desease",
        "what medicines should i take if i have coronavirus",
        "i want to help those at high risk with shopping. where can i find information on how to help?",
        "can my friends visit me?",
        "this is hateful",
        "what is the count of coronavirus infected people?",
        "i have an irritating cough",
        "is there a vaccine for coronavirus?",
        "can animal get the corona virus?",
        "incubation period of coronavirus?",
        "are there disinfectants available that can inactivate (kill) covid-19?",
        "can i lower my temperature using medication?",
        "is there a vaccine for covid-19?",
        "are quarantined visits allowed?",
        "what is the risk of covid for pregnant women?",
        "i have a fever, should i get tested?",
        "are there any travel restrictions in place yet?",
        "how long does coronavirus last",
        "can i get tested?",
        "can the government close public places?",
        "what cleaning methods kill the coronavirus?",
        "yes it is",
        "can i test myself?",
        "my eyes are burning",
        "when can i return to school?",
        "switch me to an operator",
        "i need help",
        "i am abroad who to contact?",
        "how do i avoid covid-19?",
        "why can't i get or find a mask or a respirator anywhere?",
        "how do i catch the virus?",
        "what happens when the hospital is full?",
        "how does the infection spread",
        "who is in danger",
        "sars vs corona virus?",
        "can dogs get the corona virus?",
        "who you are?",
        "i'd like a respirator",
        "how do you test",
        "what cleaning regimen should i follow",
        "how can i do my job while i'm in quarantine?",
        "covid number in my state?",
        "are people in quarantine checked?",
        "what is the best way to prevent coronavirus",
        "how does the virus spread",
        "where are cases?",
        "will i get paid leave?",
        "hello are you a living person?",
        "does eating garlic help?",
        "what medicine should i avoid taking if i have coronavirus",
        "tell me about working from home?",
        "how is flu different from corpnavirus",
        "how is covid transmitted?",
        "incubation period of coronavirus?",
        "when is the coronavirus test able to detect the disease?",
        "where are cases?",
        "is it safe to go outside?",
        "i have a sore throat",
        "go to hell",
        "a colleague is breaking quarantine what should i do?",
        "can i die from covid-19",
        "is there a medication to reduce temperature with covid-19?",
        "a national emergency was declared in the united states. what does this mean?",
        "what medicine should i take for covid 19",
        "i want to talk to a person.",
        "how does cover-19 compare to the sars epidemic?",
        "am i safe outside?",
        "spreading covid to others",
        "how long does the virus last?",
        "i want to be transferred",
        "what parks are open?",
        "does a mask or respirator help prevent covid infection?",
        "i hate these kinds of things",
        "this is crap",
        "i have illness symptoms",
        "why are no masks or respirators available anywhere?",
        "can my pets carry the virus?",
        "how would i get covid?",
        "spreading covid to others",
        "is graduation delayed?",
        "how often do i need to clean my home to prevent the spread of coronavirus?",
        "how long does the coronavirus last?",
        "do i have covid?",
        "can my pets carry the virus?",
        "how are you doing",
        "how can i get tested",
        "how do i know if i have this issue",
        "how do i know if im sick",
        "can i still attend a conference",
        "where cani get tested",
        "is lysol enough to get rid of covid virus from countertops",
        "can i get tested at walgreens?",
        "can i travel?",
        "this is crap",
        "this is hateful",
        "is graduation delayed?",
        "how do i apply for unemployment because of coid-19",
        "how can i get infected?",
        "what are the symptoms of coronoavirus",
        "when should i go to the doctor?",
        "who are you",
        "will i die from covid-19",
        "should i avoid people?",
        "is it dangerous to go outside?",
        "yes it is",
        "is rash a symptom of covid-19?",
        "i'm teaching at a school that's closed. what should i do?",
        "do i have to wear a respirator?",
        "what medicines work best",
        "when will masks be available at retail stores? they are not yet and we can get infected on public transport before they are.",
        "what measures is the us taking against covid-19?",
        "what happens if i lose my job?",
        "is the covid test able to detect infection even during the incubation period?",
        "can i go to park",
        "can a mask help me?",
        "how long will i feel terrible?",
        "what groups are most at risk",
        "why aren't there respirators?",
        "how will the shutdown impact my child's attendance records?",
        "i think i'm infected",
        "who will give me my covid test results?",
        "i was on vacation in another country.  do i need to quarantine?",
        "are grocery stores still open",
        "are the national parks closed?",
        "my child has a high fever and is coughing. what should i do?",
        "flu vs. covid-19",
        "should i avoid people?",
        "i'm in quarantine and can't work.  what should i do?",
        "washing your hands effectively",
        "are colleges open",
        "how can i get my test results?",
        "do i have covid?",
        "can my pets get the virus?",
        "what are some good tips for prevention?",
        "how does quarantine work?",
        "returning from abroad",
        "is covid transmissible from animals?",
        "is rash a symptom of covid-19?",
        "is it even possible to avoid the virus?",
        "can my friends visit me?",
        "how do you test",
        "should i quit the study abroad program?",
        "what does breathlessness look like",
        "i don't like this",
        "can i order food while in quarantine?",
        "can i go for a run outside?",
        "what is a national emergency?",
        "i do not know what to do",
        "are colleges open",
        "when does covid vacation end?",
        "what should i do",
        "how do flu symptoms differ from coronavirus symptoms?",
        "i am abroad who to contact?",
        "will i get paid leave?",
        "how many beds are available in the hospitals?",
        "when will the schools open?",
        "do i need lysol wipes?",
        "is there a vaccine?",
        "how much do i get paid for sick leave",
        "where did covid come from?",
        "how do i avoid coronavirus",
        "i need to be checked for covid 19.",
        "should i feel safe going to the movies?",
        "connect me to someone",
        "i think i might have the virus.",
        "is this worse than flu",
        "will graduations be pushed back?",
        "who is most at risk",
        "what is the first symptom",
        "how many cases of covid-19 are in the us?",
        "i have a sore throat",
        "where can i get a test kit",
        "where cani get tested",
        "how many cases are there in texas?",
        "i want to talk to an agent",
        "when should i go to a doctor?",
        "how are you",
        "i'm a doctor how can i help?",
        "who you are?",
        "can i go outside",
        "where can i get tested for cover-19",
        "do i have to quarantine",
        "how long are people infected with covid-19 before they are symptomatic?",
        "how many people have covid-19 in the whole world?",
        "i live in 78709. when will my kids high school reopen?",
        "events and large gatherings",
        "should i cancel my flight to denver?",
        "when can i get my results?",
        "how often should i wash my hands?",
        "when can i return to school?",
        "is hs 123 open?",
        "are my kids going to die?",
        "daughter is studying abroad what do we do?",
        "origin of coronavirus",
        "what is the mortality rate for covid 19",
        "what does breathlessness look like",
        "how do i know if i have this thing",
        "what should i do in quarantine?",
        "does the virus spread thru surfaces",
        "can i go out without a respirator?",
        "will i throw up if i have the virus?",
        "are the national parks closed?",
        "i live in an apartment with my girlfriend, but i am under quarantine now.  what should i do?",
        "is coronavirus contagious?",
        "does eating garlic help?",
        "number of infected",
        "how does quarantine work?",
        "how is it possible that the state does not have enough masks and respirators?",
        "how long before i get symptons?",
        "i am coughing.  should i call my doctor?",
        "what is the incubation period of covid?",
        "can pets get the virus",
        "yes it is",
        "testing spots for coronavirus?",
        "how can covid be transmitted",
        "how long can i get [paid sick leave",
        "what position does the who have?",
        "can dogs catch the corona virus",
        "who is most at risk?",
        "what cleaning methods kill the coronavirus?",
        "how long does it take to quarantine?",
        "show me the list of high-risk countries.",
        "when will my good go back to school?",
        "i have illness symptoms",
        "spreading covid to others",
        "do i get paid leave time",
        "can dogs get covid19?",
        "are people in quarantine checked?",
        "is there a vaccine for covid",
        "when will my kids school reopen",
        "can i go to the hospital?",
        "the hospital sent me home because of a lack of beds.",
        "i am abroad who should i contact?",
        "is anyone checking for compliance with those ordered to quarantine?",
        "how long is teaching on hold?",
        "will i die from covid-19",
        "i am in europe and i want to return to the united states. is that possible?",
        "will classes be moved to summer?",
        "how should i quarantine if i live with other people?",
        "can i test myself?",
        "can i test myself at my house?",
        "where can i get a covid-19 test?",
        "what is the mortality rate of the virus?",
        "what population groups are most at risk?",
        "is it dangerous to go outside?",
        "i hate this",
        "should i get tested",
        "this is hateful",
        "number of infected",
        "can you help me?",
        "am i going to die",
        "is it possible to get infected from the infected person the next day?",
        "medication that helps with coronavirus",
        "is covid a disease?",
        "should i wear a mask or a respirator?",
        "i think i have covid 19",
        "how is it going",
        "do i have covid?",
        "will graduations be pushed back?",
        "how can i get the latest news on my school closure?",
        "where can i find information about covid 19 for the world?",
        "origin of coronavirus",
        "returning from abroad",
        "i have symptoms. where can i get tested?",
        "i live in austin, where can i get tested for covid-19",
        "where can i go to get tested for covid?",
        "what are the symptoms of coronavirus",
        "is it okay to go grocery shopping?",
        "when did i need to call the doctor?",
        "is graduation delayed?",
        "spreading covid to others",
        "when does a person become contagious?",
        "how does coronavirus spread?",
        "has anyone died of coronavirus in my state?",
        "can i leave for an exchange trip?",
        "what does the who do?",
        "what can i do to prevent getting coronavirus?",
        "everything is horrible",
        "is this worse than the flu?",
        "how am i supposed to be quarantined when i live with other people?",
        "where can my kids go back to school",
        "how can i get tested for covid?",
        "where can i get screened?",
        "am i able to work from my home office?",
        "can i test myself?",
        "how long does it take to get unemployment",
        "washing your hands effectively",
        "can i get infected through a package from china",
        "how long can i get unemployment?",
        "when will covid-19 medicines be ready?",
        "i'm hanging up",
        "do i have to quarantine",
        "the hospital is full and they sent me home.",
        "effective cleaning and hand washing techqniques",
        "how many people are infected with corona virus currently in texas?",
        "can i die from covid-19",
        "ihave sore throat",
        "how long does the disease last?",
        "where cani get tested",
        "i need help",
        "this is crap",
        "how do i avoid coronavirus",
        "how dangerous is this?",
        "can i get corona virus from my pet?",
        "is this worse than flue",
        "how is a pandemic different from an epidemic?",
        "how do i stay safe",
        "how do i treat coronavirus?",
        "prevent the spread of the virus",
        "what are the common symptoms",
        "can i work from home?",
        "what are symptoms of coronvirus",
        "are colleges open",
        "my eyes are burning",
        "should i get tested if i have a cough?",
        "my husband has coronavirus symptoms",
        "what is the maximum number of people allowed to meet right now?",
        "is the covid vaccine ready?",
        "i'd like a respirator",
        "i am currently traveling out of the country. who should i contact?",
        "can my kids return to high school",
        "should i wear a respirator?",
        "are people infected in my city ?",
        "washing your hands effectively",
        "do i need to wear a face mask?",
        "i need help",
        "can i take ibuprofen if i have corona virus?",
        "what can i do to stay safe",
        "describe shortness of breath",
        "how are you",
        "how can i get tested",
        "what can i do when i'm in quarantine?",
        "where can i get masks?",
        "i'm coughing, should i go to the doctor?",
        "sars vs corona virus?",
        "why aren't there respirators?",
        "what symptoms are typical with this disease",
        "what city parks are open?",
        "is it safe to go to the grocery store?",
        "can i get tested?",
        "how long will we have to self quarantine?",
        "what is the best prevention?",
        "does covid spread by packages?",
        "is there a covid vaccine?",
        "i live in ontario, where can i get tested?",
        "where can i learn more about covid?",
        "what can i do to prevent coivd?",
        "does eating garlic help?",
        "do my test results come in the mail?",
        "i need help",
        "when do i call a doctor",
        "why aren't any masks available?",
        "what should i do when i get back from another country?",
        "should i make an appointment with my dr?",
        "my throat and head hurt",
        "how long has the national emergency been in place?",
        "can i get tested for cover?",
        "are quarantined visits allowed?",
        "should i take theraflu?",
        "how long does it last",
        "which countries have been affected?",
        "is graduation delayed?",
        "can i go to the store.",
        "ihave sore throat",
        "how many people are sick throughout the world?",
        "events and large gatherings",
        "sars vs corona virus?",
        "can i go outside?",
        "where do people get protective masks or disinfectants?",
        "has the cause of covid-19 been identified?",
        "which countries are more of a risk?",
        "how many people total have coronavirus?",
        "what should i do if the hospital won't take me in?",
        "what to do if i think i have covid?",
        "which countries has covid-19 been detected in?",
        "can i travel for work?",
        "what position does the who have?",
        "will texas provide paid sick leave",
        "i have a cough but am breathing fine, should i go to the hospital or wait?",
        "what grocery store in keller is open?",
        "how do i get tested for covid -19",
        "does the sun kill coronavirus?",
        "what parks are open?",
        "how do i get screened?",
        "how do you test",
        "what if i break quarantine?",
        "is the coronavirus the same as mers?",
        "i have a temperature and cough. do i have the coronavirus?",
        "what is the treatment for covid-19?",
        "the son is on an exchange trip",
        "can i go outside",
        "i think i'm infected",
        "who is responsible for quarantined people?",
        "when can i buy a mask?",
        "what medicine should i be taking for covid 19",
        "is graduation delayed?",
        "when can i buy a mask at a pharmacy?",
        "how do i know whether to go to the doctor?",
        "why aren't any masks available?",
        "should i see a doctor if i am showing the symptoms?",
        "we're on an exchange trip now what?",
        "how can i not get sick",
        "what has our government already done to reduce the risk of spreading the disease",
        "is coronavirus contagious?",
        "how do i protect myself?",
        "where do i go for covid19 testing?",
        "how many people have the virus in our county",
        "how can i get infected?",
        "i have a fever. should i go to the hospital?",
        "can i go to the grocery store",
        "what are the symptoms of the disease?",
        "what should i do to avoid getting sick?",
        "should i get tested if i do not have symptoms but think i've been exposed?",
        "i hate this",
        "i have a burning feeling in my chest",
        "can i get tested at home?",
        "who you are?",
        "all the stores are out of disinfecting wipes, what do i do?",
        "do i have to go to the hospital if i get covid",
        "i want to be transferred",
        "how to prevent the spread of the virus",
        "my wife is in quarantine.  do i need to be as well?",
        "how can i get tested",
        "what is shortness of breath",
        "can i return to the united states if i am abroad?",
        "returning from abroad",
        "what groups are most at risk",
        "how long should i quarrantine?",
        "can dogs get covid19?",
        "i have a fever",
        "my girlfriend has symptoms of covid-19",
        "am i allowed to go to the grocery store?",
        "how long is the incubation period?",
        "will there be a mandated quarantine",
        "can the government close public places?",
        "what is the risk of my child becoming sick with covid-19?",
        "do i have to go into quarantine?",
        "what should i do if i have been quarantined?",
        "how would i catch it?",
        "i'm hanging up",
        "where are cases?",
        "what is the test to detect covid 19?",
        "how does the state of emergency affect me?",
        "who is the most vulnerable to covid",
        "how many coronavirus cases are there in my area?",
        "can animal get the corona virus?",
        "covid number in my state?",
        "incubation period of coronavirus?",
        "will the parks and bike trails remain open?",
        "duration of paid sick leave?",
        "if i have covid how long do i have to self isoclate",
        "origin of coronavirus",
        "should i take theraflu?",
        "when should i wear a mask?",
        "returning from abroad",
        "do we have enough protective measures?",
        "how is it going",
        "how long should i be in quarantine?",
        "is there a vaccine for the coronavirus?",
        "if i have syptoms, how long should i quartine for?",
        "can pets get covid",
        "how many people are infected",
        "do i need to get tested?",
        "can pets get covid",
        "everything is horrible",
        "will i get paid leave?",
        "when can my kids go back to high school in 78712",
        "do i need to do both?",
        "what are symtoms?",
        "who you are?",
        "can pets contract the virus",
        "can i work from home?",
        "how many people in texas have corona virus?",
        "what rules should i follow to prevent covid illness?",
        "what are symptoms of coronvirus",
        "testing spots for coronavirus?",
        "i have a sore throat",
        "do i get paid leave time",
        "do i need lysol wipes?",
        "i have headache and sore throat ..what should i do ?",
        "am i sick",
        "is there a cure for covid-19?",
        "when can i get my results?",
        "origin of coronavirus",
        "is it safe to fly to seattle?",
        "connect me to someone",
        "can i get tested at my doctor's?",
        "what can you do",
        "how can i prevent coronavirus",
        "how can covid be transmitted",
        "what are the risky countries?",
        "how is covid transmitted?",
        "spreading covid to others",
        "i want to switch to an operator.",
        "when will the ncaa championships be held?",
        "duration of paid sick leave?",
        "flu vs. covid-19",
        "what should i do",
        "who are you",
        "how long should you self-quarantine?",
        "i hate this",
        "is hs 123 open?",
        "how does this work",
        "washing your hands effectively",
        "i don't like this",
        "am i allowed to go to my garden in quarantine?",
        "is the government legally allowed to close shops and restaurants?",
        "should i spray myself or my kids with disinfectant?",
        "where are cases?",
        "what should i do if i returned from another country?",
        "what are symptoms of coronvirus",
        "how long can i expect to be sick?",
        "can i receive visits during quarantine?",
        "when will schools close?",
        "am i safe outside?",
        "are events being shut down?",
        "can medication be used to reduce fever?",
        "how does quarantine work?",
        "am i sick",
        "how to wash your hands properly?",
        "i'm working at a school that's closed now. what should i do?",
        "who to contact when i'm in the high risk area",
        "why is the government shutting down my event?",
        "can you help me?",
        "can i go to grocery stores",
        "how do i know if i'm suffering from shortness of breath",
        "where can i find more information about covid 19?",
        "i am on a exchange trip, should i cancel it?",
        "returning from abroad",
        "yes it is",
        "events and large gatherings",
        "how long is the incubation period for covid-19",
        "is there a cure for covid-19?",
        "how can covid be transmitted",
        "can i get tested",
        "i just travelled. what do i do?",
        "can i still get paid sick leave for 14 days if i get corona",
        "will there be school in the summer?",
        "can i still go to the grocery store?",
        "what are the common symptoms",
        "when can i be ordered to quarantine?",
        "should i wear a respirator?",
        "my girlfriend has symptoms of covid-19",
        "do i need lysol wipes?",
        "returning from abroad",
        "how do i get screened?",
        "ihave sore throat",
        "when is school back in session?",
        "how long does it last?",
        "can pets get covid",
        "how long does the virus last",
        "is the coronavirus the same as a cold?",
        "what is a pandemic?",
        "my doctor hasn't given me my test results back yet.",
        "when will the schools open?",
        "testing spots for coronavirus?",
        "sars vs corona virus?",
        "i have illness symptoms",
        "will there be exams in the summer?",
        "can i travel for work?",
        "can i work from home during quarantine?",
        "how long does covid-19 last?",
        "connect me to someone",
        "which age group is at an increased risk of getting covid 19?",
        "what will help me prevent covid infection?",
        "how many people have the virus?",
        "if a member of my family is in quarantine, what should i do?",
        "if i am in quarantine, can i go for walks?",
        "where can i get screened?",
        "is there a nationwide curfew?",
        "how is flu different from corpnavirus",
        "my child is coughing. should i be worried?",
        "how long will i feel terrible?",
        "is there a cure for covid 19?",
        "i want to help i'm a student.",
        "can my child go to school?",
        "what should i do to contain the spread of the virus",
        "how long do i have to be stuck at home?",
        "will i die from covid-19",
        "where did corona virus start from?",
        "when should i wear a respirator?",
        "how long before i get symptons?",
        "i thing i feel symptoms of the disease",
        "does alcohol kill the coronavirus?",
        "how is the united states prepared for the spread of covid 19?",
        "how long will the state of emergency last?",
        "i am in new york where should i get tested",
        "are grocery stores still open",
        "can a mask help me?",
        "i have a question about unemployment",
        "how long will it be until there is a vaccine?",
        "will i poop a lot if i have the virus?",
        "in the event there is a large number of infected and hospitals can't manage to treat everyone what is recommended treatment for home quarantine and self-medication?",
        "can i travel?",
        "why aren't there respirators?",
        "is coronavirus contagious?",
        "can i get tested at home?",
        "who am i talking to",
        "how to treat covid?",
        "when will the nhl return?",
        "who am i talking to",
        "when should i wear a mask?",
        "how long is the incubation period of covid 19?",
        "how to distinguish it from a common cold.",
        "how do i catch the virus?",
        "what medicines work best",
        "can i go to the hospital?",
        "when will the national emergency end?",
        "what if i have a roommate and i'm put under quarantine?",
        "is there a vaccine for covid-19",
        "i'm hanging up",
        "number of infected",
        "is this the same as the flu?",
        "is this worse than the flu?",
        "can i get tested?",
        "under what circumstances do i have to quarantine?",
        "i have cancer am i at risk of coronavirus?",
        "can i get tested quickly?",
        "can i go outside?",
        "when does covid vacation end?",
        "should i go to the doctor now",
        "is this worse than flue",
        "is covid transmissible from animals?",
        "i'd like a respirator",
        "can i get tested quickly?",
        "is it possible to detect the disease during the incubation period?",
        "what has the world health organization said about covid 19?",
        "how does the infection spread",
        "best vitamin to take",
        "is covid a disease?",
        "how long does it take to develop a vaccine?",
        "what can you do",
        "i want to help with shopping for the old.",
        "i need help",
        "how to avoid catching covid-19.",
        "can i travel in the current emergency situation?",
        "how long does it last",
        "should i go to the hospital",
        "i heard about a medication for coronavirus treatment",
        "can i go to the gym or should i avoid it?",
        "how much paid sick leave will i get if i am contracted with the virus?",
        "how many current cases are there in illinois",
        "how do i know if i got this thing",
        "where can i get tested in alabama",
        "which countries should i avoid?",
        "is it possible to estimate how long it will take to administer the drug / vaccine to people?",
        "what countries are under a quarantine?",
        "origin of coronavirus",
        "how can i apply for unemployment during this outbreak?",
        "what can i do to not get sick?",
        "what opinion does the world health organization (who) have on next steps?",
        "can i get tested",
        "are there any cases near me",
        "should i change my travel plans?",
        "when will the schools open?",
        "how do i get screened?",
        "i want to help with babysitting.",
        "how is covid transmitted?",
        "can i go outside",
        "incubation period of coronavirus?",
        "how are you",
        "is this worse than flue",
        "can i get tested",
        "how long do symptons take to develop ?",
        "where are cases?",
        "what is the most effective prevention?",
        "where are cases?",
        "origin of coronavirus",
        "can a mask help me?",
        "will a respirator help me?",
        "i hate you",
        "who should i call if i have symptoms?",
        "this is crap",
        "who is most at risk?",
        "how long should you self-quarantine?",
        "can pets contract the virus",
        "i'm afraid and don't know what to do",
        "are groups of people allowed to meet?",
        "how long does coronavirus last",
        "can i still go grocery shopping",
        "can i travel out of the country?",
        "when will masks be available?",
        "how do i apply for unemployment benefits due to covid-19?",
        "what can you help me with",
        "how many people ar sick in the us?",
        "does the sun kill coronavirus?",
        "how do you test",
        "where should i go if i suspect i have coronavirus?",
        "i'm hanging up",
        "how long do i need to quarantine before i no longer can transmit the virus?",
        "are quarantined visits allowed?",
        "how should i properly wash my hands?",
        "i need medicine. can i go to the store?",
        "what is effective prevention against covid?",
        "who are you",
        "i have symptoms. should i get tested?",
        "how long does the virus last?",
        "does eating garlic help?",
        "what is the most effective prevention?",
        "what does a pandemic mean?",
        "why aren't there respirators?",
        "can dogs get the coronavirus?",
        "where did corona virus start from?",
        "is it contagious",
        "how do i know if i'm sick with covid-19?",
        "can medication reduce fever caused by a possible covid infection?",
        "will i die if i get coronavirus>",
        "can you direct me to the nearest test center",
        "who is most at risk?",
        "why aren't there enough masks and respirators?",
        "should i buy a respirator?",
        "when do i know if i need to quarantine?",
        "how to treat covid?",
        "can dogs spread the corona virus?",
        "what medicine work best for treatment ?",
        "testing spots for coronavirus?",
        "is hs 123 open?",
        "do i have to use bleach to kill coronavirus?",
        "where can i get screened?",
        "i think i'm infected",
        "how is covid transmitted?",
        "ihave sore throat",
        "when will the nhl return?",
        "where should i go to get screened",
        "whats the difference between cleaning and disinfecting?",
        "what are the symptoms i should look out for",
        "is it possible to get infected with coronavirus if i have my goods shipped from chinese stores?",
        "i have sore throat, is it coronavirus?",
        "how long does the corona virus last?",
        "who do i contact if i want to get tested for covid 19 infection?",
        "how do i stay safe",
        "how do we treat covid?",
        "is a headache a symptom of the coronavirus?",
        "how do i wash my hands properly?",
        "will government employees be paid during sick leave?",
        "will i get a refund for a ticket i purchased?",
        "how do i know if my concert is cancelled?",
        "i feel congested and have a fever",
        "what is a safe distance when someone brings me groceries?",
        "i'm hanging up",
        "can i still attend a conference",
        "what is the difference between covid-19 and the flu",
        "this is crap",
        "what is the risk of coronavirus for pregnant women?",
        "how many beds are available for covid-19 patients?",
        "how do i stay safe",
        "does the us have a confirmed covid case?",
        "how long before i experience covid-19 symptons?",
        "does eating garlic help?",
        "should my child stay home from school?",
        "is there a vaccine for covid-19?",
        "can i go to the grocery store or will i catch corona",
        "do i need to stay home",
        "how do i know if i got this",
        "do i have covid?",
        "where did the coronavirus come from?",
        "what measurements is the government taking?",
        "what are symtoms?",
        "who is responsible for quarantined people?",
        "are the local parks open?",
        "what should i do if i live by myself and i'm in quarantine?",
        "if i think i have covid-19, should i see my dr?",
        "what is shortness of breath",
        "where did covid come from?",
        "is covid the same as the flu?",
        "i have travled recently. what do i do?",
        "yes it is",
        "describe shortness of breath",
        "can i travel?",
        "what does a pandemic mean?",
        "i have a fever",
        "is anyone allowed to visit during quarantine?",
        "when can i return to the united states?",
        "my eyes are burning",
        "what exactly is home quarantine?",
        "am i going to die from the covid virus?",
        "do i need a doctor's note to travel?",
        "should i wear a respirator?",
        "what kind of medicine should i take",
        "if infected, how long should individuals self-quarantine?",
        "does ma have a confirmed covid case?",
        "does alcohol kill the coronavirus?",
        "where can i get masks?",
        "are you a robot?",
        "what is the hospital capacity for covid 19 patients?",
        "should i get tested for covid-19?",
        "when should i call a doctor",
        "can my pets get the virus?",
        "how long does it last",
        "does covid spread by packages?",
        "is the us well prepared for covid 19",
        "is it possible to test for covid 19 during the incubation period?",
        "i'm hanging up",
        "is it ok for me to go to the grocery store",
        "how can i get screened",
        "can i visit relatives in another state?",
        "how does quarantine work?",
        "when will covid-19 medicines be ready?",
        "what are the risky countries?",
        "what can i ask you",
        "i'm afraid i have covid-19",
        "what if i live alone and can't go out to buy food?",
        "prevent the spread of the virus",
        "can i take a sick leave to quarantine?",
        "can i get tested for cover?",
        "i'm a medical student and i want to get involved. how can i help?",
        "why aren't there respirators?",
        "what is the mortality rate of covid-19?",
        "medication that helps with coronavirus",
        "which countries should i avoid?",
        "i want to talk to someone."
    ]
}